takumitools/__init__.py
takumitools/apiclient_base.py
takumitools/code_generator.py
takumitools/spec_reader.py
takumitools-0.1.1.dist-info/LICENSE
takumitools-0.1.1.dist-info/METADATA
takumitools-0.1.1.dist-info/WHEEL
takumitools-0.1.1.dist-info/RECORD
