Metadata-Version: 2.1
Name: takumitools
Version: 0.1.1
Summary: A toolkit for generating Python API clients from OpenAPI specifications, providing dynamic request handling, robust exception handling, and support for various content types.
Author: Ali Tavallaie
Author-email: a.tavallaie@gmail.com
Requires-Python: >=3.10,<4.0
Classifier: Programming Language :: Python :: 3
Classifier: Programming Language :: Python :: 3.10
Classifier: Programming Language :: Python :: 3.11
Classifier: Programming Language :: Python :: 3.12
